<?xml version="1.0" encoding="utf-8"?><pluginstrument><aircraft>Beech H35</aircraft><type>Fuel Selector Valve</type><uuid>05f49148-564b-468f-8a51-8eb9ce1f315c</uuid><author>Simstrumentation</author><description>Fuel Tank Selector for Beechcraft Bonanza.

Should work with any plane that has a 3 position Off / Left / Right style selector.</description><compatibleFSX>true</compatibleFSX><compatibleP3D>false</compatibleP3D><compatibleXPL>false</compatibleXPL><compatibleFS2>false</compatibleFS2><compatibleFS2020>false</compatibleFS2020><version>1</version><configVersion>1</configVersion><pluginInterfaceVersion>100</pluginInterfaceVersion><prefWidth>716</prefWidth><prefHeight>700</prefHeight><source>ONLINE</source><platforms><platform>WINDOWS</platform><platform>MAC</platform><platform>LINUX</platform><platform>RASPBERRY_PI</platform><platform>ANDROID</platform><platform>IPAD</platform><platform>ESP32</platform></platforms><tiers><tier>HOME_USE_STANDARD</tier></tiers></pluginstrument>